contract_analysis/__init__.py
contract_analysis/content_understanding.py
contract_analysis/contract_analysis.py
contract_analysis/document.py
contract_analysis/document_intelligence.py
contract_analysis/openai_gpt.py
contract_analysis/translation.py
contract_analysis-0.1.3.dist-info/METADATA
contract_analysis-0.1.3.dist-info/WHEEL
contract_analysis-0.1.3.dist-info/licenses/LICENSE
contract_analysis-0.1.3.dist-info/RECORD
