Metadata-Version: 2.3
Name: contract-analysis
Version: 0.1.3
Summary: A Python library for analyzing legal contracts using Azure services.
Author-email: Iaroslav Sedrichev <iasedric@microsoft.com>
License: MIT
Classifier: Development Status :: 3 - Alpha
Classifier: Intended Audience :: Developers
Classifier: License :: OSI Approved :: MIT License
Classifier: Operating System :: Microsoft :: Windows
Classifier: Programming Language :: Python :: 3
Classifier: Topic :: Software Development :: Libraries
Requires-Python: >=3.8
Requires-Dist: azure-ai-formrecognizer
Requires-Dist: azure-core
Requires-Dist: azure-identity
Requires-Dist: openai
Requires-Dist: pywin32; sys_platform == 'win32'
Requires-Dist: pyyaml
Requires-Dist: requests
Provides-Extra: test
Requires-Dist: coverage; extra == 'test'
Requires-Dist: pytest; extra == 'test'
